python_poetry_template/__init__.py
python_poetry_template/maths/__init__.py
python_poetry_template/maths/functions.py
python_poetry_template-1.0.0.dist-info/METADATA
python_poetry_template-1.0.0.dist-info/WHEEL
python_poetry_template-1.0.0.dist-info/RECORD
