Metadata-Version: 2.1
Name: python-poetry-template
Version: 1.0.0
Summary: Plantilla para desarrollo fluido en Python
Author: frapercan
Author-email: frapercan1@alum.us.es
Requires-Python: >=3.10,<4.0
Classifier: Programming Language :: Python :: 3
Classifier: Programming Language :: Python :: 3.10
Classifier: Programming Language :: Python :: 3.11
Requires-Dist: docopt (>=0.6.2,<0.7.0)
